[
    {
        "artist": "张哲瀚",
        "name": "环绕",
        "type": "album",
        "url": "https://music.163.com/store/m/album/receive/update?tk=ab69d3c235d190d90b5abdc822079425&s=8dfa46c9a8964b6e9af81dac1a05c94b",
        "short_url": "http://t.cn/A6f8Y0Nv",
        "weibo_url": "https://weibo.com/detail/4661071862304655"
    },
    {
        "artist": "李润祺",
        "name": "做勇敢的大人",
        "type": "song",
        "url": "https://music.163.com/store/m/song/receive?tk=d632a85629d32825a72c4a6a2a72cc66&s=f680dd60123c41a587838ed3c883d72c",
        "short_url": "http://t.cn/A6fEmAWB",
        "weibo_url": "https://weibo.com/detail/4661665692125860"
    },
    {
        "artist": "胡烨韬",
        "name": "UGLY",
        "type": "song",
        "url": "https://music.163.com/store/m/song/receive?tk=1577cea2aaa3e87ee99beeabde70ceff&s=0aface19ef084f3e87e00b9389c55078",
        "short_url": "http://t.cn/A6fELu2p",
        "weibo_url": "https://weibo.com/detail/4661468680949372"
    }
]