[
    {
        "days": 7,
        "goods": "黑胶VIP(7天)",
        "senderId": 270229883,
        "url": "https://music.163.com/prime/m/gift-receive?d=t3824zQD2w6ISa-9FZgUcg&p=L3y_iCFu7phXqnPHZsGXaD9NF01aNM18k2ZZgEKqjveWKqZnEt0nOzlV-KFNqJfOX2GSiYd9Tw1ZJhaJiBWPF3u-ei-iz8aDtcKlB1M7VQM&userid=270229883&app_version=8.10.60&dlt=0846",
        "short_url": "https://weibo.cn/sinaurl?u=https%3A%2F%2Fmusic.163.com%2Fprime%2Fm%2Fgift-receive%3Fd%3Dt3824zQD2w6ISa-9FZgUcg%26p%3DL3y_iCFu7phXqnPHZsGXaD9NF01aNM18k2ZZgEKqjveWKqZnEt0nOzlV-KFNqJfOX2GSiYd9Tw1ZJhaJiBWPF3u-ei-iz8aDtcKlB1M7VQM%26userid%3D270229883%26app_version%3D8.10.60%26dlt%3D0846",
        "weibo_url": "https://weibo.com/detail/4947396037446911",
        "webUrl": "https://music.163.com/prime/m/gift-mypurchase?orderid=482059792&giftSrc=3&nm_style=sbt&bounces=false"
    },
    {
        "days": 7,
        "goods": "黑胶VIP(7天)",
        "senderId": 548881119,
        "url": "https://music.163.com/prime/m/gift-receive?d=Jk4hi7Uh4ou4siJ0bkkNow&p=QbDcirmyM7zXoX9MbjTW8TiES6zqZUlY9R3mGJflmHCPpQPWtkai8FIm8wTK6ix_WokNC-8hqi7xH_3z33kmtKRxneZ8EKOsF_o374SDuZg&userid=548881119&app_version=8.10.71&dlt=0846",
        "short_url": "https://weibo.cn/sinaurl?u=https%3A%2F%2Fmusic.163.com%2Fprime%2Fm%2Fgift-receive%3Fd%3DJk4hi7Uh4ou4siJ0bkkNow%26p%3DQbDcirmyM7zXoX9MbjTW8TiES6zqZUlY9R3mGJflmHCPpQPWtkai8FIm8wTK6ix_WokNC-8hqi7xH_3z33kmtKRxneZ8EKOsF_o374SDuZg%26userid%3D548881119%26app_version%3D8.10.71%26dlt%3D0846",
        "weibo_url": "https://weibo.com/detail/4947238277351185",
        "webUrl": "https://music.163.com/prime/m/gift-mypurchase?orderid=481705088&giftSrc=3&nm_style=sbt&bounces=false"
    },
    {
        "days": 7,
        "goods": "黑胶VIP(7天)",
        "senderId": 514866776,
        "url": "https://music.163.com/prime/m/gift-receive?d=QZPGpiaG3uK4FG7UaTVMkQ&p=NaGlpr52t9Y7xdQxrSrF9esVtVmf1bpXrED6avhI-JIvwH5c6pcHeolFSAQN6nG-fPMqXSeHbzlNSuzjGTvu-FPpbpOGhIiazgnyOoM5cyo&userid=514866776&app_version=8.10.60&dlt=0846",
        "short_url": "https://weibo.cn/sinaurl?u=https%3A%2F%2Fmusic.163.com%2Fprime%2Fm%2Fgift-receive%3Fd%3DQZPGpiaG3uK4FG7UaTVMkQ%26p%3DNaGlpr52t9Y7xdQxrSrF9esVtVmf1bpXrED6avhI-JIvwH5c6pcHeolFSAQN6nG-fPMqXSeHbzlNSuzjGTvu-FPpbpOGhIiazgnyOoM5cyo%26userid%3D514866776%26app_version%3D8.10.60%26dlt%3D0846",
        "weibo_url": "https://weibo.com/detail/4946906179962304",
        "webUrl": "https://music.163.com/prime/m/gift-mypurchase?orderid=481536586&giftSrc=3&nm_style=sbt&bounces=false"
    },
    {
        "days": 7,
        "goods": "黑胶VIP(7天)",
        "senderId": 120896216,
        "url": "https://music.163.com/prime/m/gift-receive?d=q8huR1KQwXpiTM8E3NRKIg&p=xpYbWFrhpmnpRArYW8IBJeWCYZ6PEemjOPnItuQ07h5eiHDWjDnrakE--RsGyZLdewFB5JP0jyBhOVtX_9AIbEybk2Msdno1jl2zKhZl0SM&userid=120896216&app_version=8.10.71&dlt=0846",
        "short_url": "https://weibo.cn/sinaurl?u=https%3A%2F%2Fmusic.163.com%2Fprime%2Fm%2Fgift-receive%3Fd%3Dq8huR1KQwXpiTM8E3NRKIg%26p%3DxpYbWFrhpmnpRArYW8IBJeWCYZ6PEemjOPnItuQ07h5eiHDWjDnrakE--RsGyZLdewFB5JP0jyBhOVtX_9AIbEybk2Msdno1jl2zKhZl0SM%26userid%3D120896216%26app_version%3D8.10.71%26dlt%3D0846",
        "weibo_url": "https://weibo.com/detail/4946721395184184",
        "webUrl": "https://music.163.com/prime/m/gift-mypurchase?orderid=481218251&giftSrc=3&nm_style=sbt&bounces=false"
    },
    {
        "days": 7,
        "goods": "黑胶VIP(7天)",
        "senderId": 510481945,
        "url": "https://music.163.com/prime/m/gift-receive?d=wbPO0MhBhRKztO8bxj2rDQ&p=FDuaUqZIdPkjQZ3vn9dndELEQry05rE9We6xTzae15_rXbcjOh5AKOVBbGoBaPp2vUv_QoCI7RfBH4EshZJGXA0sOneHlU0Ld05U55Ug0jg&userid=510481945&app_version=8.10.71&dlt=0846",
        "short_url": "https://weibo.cn/sinaurl?u=https%3A%2F%2Fmusic.163.com%2Fprime%2Fm%2Fgift-receive%3Fd%3DwbPO0MhBhRKztO8bxj2rDQ%26p%3DFDuaUqZIdPkjQZ3vn9dndELEQry05rE9We6xTzae15_rXbcjOh5AKOVBbGoBaPp2vUv_QoCI7RfBH4EshZJGXA0sOneHlU0Ld05U55Ug0jg%26userid%3D510481945%26app_version%3D8.10.71%26dlt%3D0846",
        "weibo_url": "https://weibo.com/detail/4946234865617153",
        "webUrl": "https://music.163.com/prime/m/gift-mypurchase?orderid=480751325&giftSrc=3&nm_style=sbt&bounces=false"
    }
]