[
    {
        "days": 7,
        "goods": "黑胶VIP(7天)",
        "senderId": 430666851,
        "url": "https://music.163.com/prime/m/gift-receive?u=41a17f27783840a89b52173d0bc18bee863e0532469e4eadb4772a4cddc6ea69&userid=430666851&app_version=8.5.20",
        "short_url": "http://t.cn/A6IFVhOM",
        "weibo_url": "https://weibo.com/detail/4680562926947369",
        "webUrl": "https://music.163.com/prime/m/gift-mypurchase?orderid=190596235&giftSrc=3&nm_style=sbt&bounces=false"
    },
    {
        "days": 7,
        "goods": "黑胶VIP(7天)",
        "senderId": 80791172,
        "url": "https://music.163.com/prime/m/gift-receive?u=7248514e1d1149389a075bd2351c7ce6efb8d98d9a314c83ae816bcddac6d2c8",
        "short_url": "http://t.cn/A6IkIOhT",
        "weibo_url": "https://weibo.com/detail/4680233058566973",
        "webUrl": "https://music.163.com/prime/m/gift-mypurchase?orderid=190373851&giftSrc=3&nm_style=sbt&bounces=false"
    },
    {
        "days": 7,
        "goods": "黑胶VIP(7天)",
        "senderId": 74922984,
        "url": "https://music.163.com/prime/m/gift-receive?u=d259ebede7f54c819b7f518ebf8936f4dbeed27580834497980481b940d50d94&userid=74922984&app_version=8.5.10",
        "short_url": "http://t.cn/A6Inqnsh",
        "weibo_url": "https://weibo.com/detail/4680278397945036",
        "webUrl": "https://music.163.com/prime/m/gift-mypurchase?orderid=187717035&giftSrc=3&nm_style=sbt&bounces=false"
    },
    {
        "days": 7,
        "goods": "黑胶VIP(7天)",
        "senderId": 52884010,
        "url": "https://music.163.com/prime/m/gift-receive?u=e4c4be98074c4e61a24343166a925e1d1a164846b1a24d019b3175f4e481eba1",
        "short_url": "http://t.cn/A6IknZ8F",
        "weibo_url": "https://weibo.com/detail/4680373877342895",
        "webUrl": "https://music.163.com/prime/m/gift-mypurchase?orderid=188401777&giftSrc=3&nm_style=sbt&bounces=false"
    },
    {
        "days": 7,
        "goods": "黑胶VIP(7天)",
        "senderId": 357010274,
        "url": "https://music.163.com/prime/m/gift-receive?u=2dab0539b8884974898b59f8c5f94e0de2dd649be6bf465ba775ffa08ddc0af8&userid=357010274&app_version=8.5.20",
        "short_url": "http://t.cn/A6IkrhJm",
        "weibo_url": "https://weibo.com/detail/4680397630474568",
        "webUrl": "https://music.163.com/prime/m/gift-mypurchase?orderid=190413945&giftSrc=3&nm_style=sbt&bounces=false"
    },
    {
        "days": 5,
        "goods": "黑胶VIP(5天)",
        "senderId": 1910879094,
        "url": "https://music.163.com/prime/m/gift-receive?u=09064c2539534ed5bfb149d79243228cb9e669c76db24413bcbb22e0ef0f680c",
        "short_url": "http://t.cn/A6IDpQTh",
        "weibo_url": "https://weibo.com/detail/4679972839756809",
        "webUrl": "https://music.163.com/prime/m/gift-mypurchase?orderid=188612988&giftSrc=3&nm_style=sbt&bounces=false"
    },
    {
        "days": 5,
        "goods": "黑胶VIP(5天)",
        "senderId": 315908816,
        "url": "https://music.163.com/prime/m/gift-receive?u=15b0fd1eb4b746f48b5c6f42ab318021b490e0e26e6c4f7ea5d151b257d674fc",
        "short_url": "http://t.cn/A6IkKtEH",
        "weibo_url": "https://weibo.com/detail/4680283657604433",
        "webUrl": "https://music.163.com/prime/m/gift-mypurchase?orderid=190184511&giftSrc=3&nm_style=sbt&bounces=false"
    },
    {
        "days": 5,
        "goods": "黑胶VIP(5天)",
        "senderId": 492691507,
        "url": "https://music.163.com/prime/m/gift-receive?u=c863ad34121b4b0c80e17796c034e44ede637af9827b4ae9ac797d99737756c4",
        "short_url": "http://t.cn/A6IDeq4k",
        "weibo_url": "https://weibo.com/detail/4680091853128131",
        "webUrl": "https://music.163.com/prime/m/gift-mypurchase?orderid=190183820&giftSrc=3&nm_style=sbt&bounces=false"
    },
    {
        "days": 5,
        "goods": "黑胶VIP(5天)",
        "senderId": 1608984062,
        "url": "https://music.163.com/prime/m/gift-receive?u=5e6e76b53df9412da6aaf64b5e7f652e13c1a6deaf3949c3937f8eada64065ce",
        "short_url": "http://t.cn/A6IkestE",
        "weibo_url": "https://weibo.com/detail/4680413736339026",
        "webUrl": "https://music.163.com/prime/m/gift-mypurchase?orderid=188067328&giftSrc=3&nm_style=sbt&bounces=false"
    },
    {
        "days": 5,
        "goods": "黑胶VIP(5天)",
        "senderId": 1751298904,
        "url": "https://music.163.com/prime/m/gift-receive?u=e7469885d60b45deafdd10ebdd247b77d37cbe14ff694c6a9b34ecb4b4f4e3ec",
        "short_url": "http://t.cn/A6IknDZJ",
        "weibo_url": "https://weibo.com/detail/4680377610538175",
        "webUrl": "https://music.163.com/prime/m/gift-mypurchase?orderid=190397590&giftSrc=3&nm_style=sbt&bounces=false"
    }
]