[
    {
        "days": 7,
        "senderId": 78162637,
        "url": "https://music.163.com/prime/m/gift-receive?u=104bb48e6cb7411395350f14b141c7abbe0ac47d77844a93a67832a66070f4af",
        "short_url": "http://t.cn/A6fMtcc8",
        "weibo_url": "https://weibo.com/detail/4654282445426858",
        "webUrl": "https://music.163.com/prime/m/gift-mypurchase?orderid=171851489&giftSrc=3&nm_style=sbt&bounces=false"
    },
    {
        "days": 7,
        "senderId": 246648878,
        "url": "https://music.163.com/prime/m/gift-receive?u=281d9cd42bb8448884ffd1389723a2e9cfb43032cf4741e98d88dd69d220ed06",
        "short_url": "http://t.cn/A6fM4zC2",
        "weibo_url": "https://weibo.com/detail/4654271402871558",
        "webUrl": "https://music.163.com/prime/m/gift-mypurchase?orderid=171863024&giftSrc=3&nm_style=sbt&bounces=false"
    },
    {
        "days": 7,
        "senderId": 1357692878,
        "url": "https://music.163.com/prime/m/gift-receive?u=5e99101caf224e94b895f2b65435c5b6c473243ea3f74015ab0aeaa415bd5825",
        "short_url": "http://t.cn/A6fMfLRh",
        "weibo_url": "https://weibo.com/detail/4654288897577244",
        "webUrl": "https://music.163.com/prime/m/gift-mypurchase?orderid=171881844&giftSrc=3&nm_style=sbt&bounces=false"
    },
    {
        "days": 7,
        "senderId": 1689847354,
        "url": "https://music.163.com/prime/m/gift-receive?u=af235a680818454ba441e93e61942fc3235422072b364880b05dcb75a1d9a3bf",
        "short_url": "http://t.cn/A6fMiYQ9",
        "weibo_url": "https://weibo.com/detail/4654302411100600",
        "webUrl": "https://music.163.com/prime/m/gift-mypurchase?orderid=171892732&giftSrc=3&nm_style=sbt&bounces=false"
    },
    {
        "days": 7,
        "senderId": 128706590,
        "url": "https://music.163.com/prime/m/gift-receive?u=c8509e78e2c14ad18000f05467f2f5fca608f6e446054e9ea9cdf9c09c5fcfab",
        "short_url": "http://t.cn/A6fME4zZ",
        "weibo_url": "https://weibo.com/detail/4654431684265321",
        "webUrl": "https://music.163.com/prime/m/gift-mypurchase?orderid=172107641&giftSrc=3&nm_style=sbt&bounces=false"
    },
    {
        "days": 7,
        "senderId": 338746972,
        "url": "https://music.163.com/prime/m/gift-receive?u=f9daa922ddbc4d33a85217a87229c9bc6c0f80c226c04627951eeafd01d38e5d",
        "short_url": "http://t.cn/A6fME5YB",
        "weibo_url": "https://weibo.com/detail/4654432015354405",
        "webUrl": "https://music.163.com/prime/m/gift-mypurchase?orderid=171912150&giftSrc=3&nm_style=sbt&bounces=false"
    },
    {
        "days": 7,
        "senderId": 49720282,
        "url": "https://music.163.com/prime/m/gift-receive?u=13794cb0319f487b94be541ecb225c9ee2ac334cdf5146289d308b3a6f3c31bc",
        "short_url": "http://t.cn/A6fIWnT1",
        "weibo_url": "https://weibo.com/detail/4654089789244345",
        "webUrl": "https://music.163.com/prime/m/gift-mypurchase?orderid=171689632&giftSrc=3&nm_style=sbt&bounces=false"
    },
    {
        "days": 7,
        "senderId": 1766966214,
        "url": "https://music.163.com/prime/m/gift-receive?u=457a788a765b4991be9c61b4e979b9089493a894a0fc43b0bf8bf108e6f0f746",
        "short_url": "http://t.cn/A6fMaPJi",
        "weibo_url": "https://weibo.com/detail/4654309297881996",
        "webUrl": "https://music.163.com/prime/m/gift-mypurchase?orderid=171880479&giftSrc=3&nm_style=sbt&bounces=false"
    },
    {
        "days": 7,
        "senderId": 513931868,
        "url": "https://music.163.com/prime/m/gift-receive?u=2214907165ad4b4383851941f2790dc59e209f9cca39424593bfbfdcbbb73377",
        "short_url": "http://t.cn/A6fM8nih",
        "weibo_url": "https://weibo.com/detail/4654425437636488",
        "webUrl": "https://music.163.com/prime/m/gift-mypurchase?orderid=171823020&giftSrc=3&nm_style=sbt&bounces=false"
    },
    {
        "days": 7,
        "senderId": 425363710,
        "url": "https://music.163.com/prime/m/gift-receive?u=e7bb90792bc943eab3a9d273bce5eecffee812b063d6454e915631e6de308e06",
        "short_url": "http://t.cn/A6fM9RNc",
        "weibo_url": "https://weibo.com/detail/4654341564662152",
        "webUrl": "https://music.163.com/prime/m/gift-mypurchase?orderid=171887542&giftSrc=3&nm_style=sbt&bounces=false"
    },
    {
        "days": 5,
        "senderId": 405211605,
        "url": "https://music.163.com/prime/m/gift-receive?u=03fa93bafe584f5f8877ff08cf68d8c3ca3cfb7545dd40938ba0fb1653168dee",
        "short_url": "http://t.cn/A6fM4CpW",
        "weibo_url": "https://weibo.com/detail/4654271940007994",
        "webUrl": "https://music.163.com/prime/m/gift-mypurchase?orderid=171826029&giftSrc=3&nm_style=sbt&bounces=false"
    },
    {
        "days": 5,
        "senderId": 468979915,
        "url": "https://music.163.com/prime/m/gift-receive?u=064c4dae6e524cd79281d71e4426a4c8da9ee3218120442daade2524fdb9af06",
        "short_url": "http://t.cn/A6fMPjA6",
        "weibo_url": "https://weibo.com/detail/4654215543131251",
        "webUrl": "https://music.163.com/prime/m/gift-mypurchase?orderid=171817390&giftSrc=3&nm_style=sbt&bounces=false"
    },
    {
        "days": 5,
        "senderId": 1485034256,
        "url": "https://music.163.com/prime/m/gift-receive?u=71026efdd3e54843b65ff9d1b15d2bb90cd11e4f0c3241b184d0301956a85bee",
        "short_url": "http://t.cn/A6fI3SLq",
        "weibo_url": "https://weibo.com/detail/4654157065357044",
        "webUrl": "https://music.163.com/prime/m/gift-mypurchase?orderid=171761564&giftSrc=3&nm_style=sbt&bounces=false"
    },
    {
        "days": 5,
        "senderId": 1863588381,
        "url": "https://music.163.com/prime/m/gift-receive?u=74fbfc611bfc479e92e89b4a49c74cc0442c3f001a224e9386e3ac1dac527fb7",
        "short_url": "http://t.cn/A6fMM7tp",
        "weibo_url": "https://weibo.com/detail/4654293167113072",
        "webUrl": "https://music.163.com/prime/m/gift-mypurchase?orderid=171876178&giftSrc=3&nm_style=sbt&bounces=false"
    },
    {
        "days": 5,
        "senderId": 568430360,
        "url": "https://music.163.com/prime/m/gift-receive?u=a83fb0faca984ff58ef3d14f9b9ae970775f90b9a9ca4c67b68367f83f422bf5",
        "short_url": "http://t.cn/A6fIB28M",
        "weibo_url": "https://weibo.com/detail/4654159675261992",
        "webUrl": "https://music.163.com/prime/m/gift-mypurchase?orderid=171777083&giftSrc=3&nm_style=sbt&bounces=false"
    },
    {
        "days": 5,
        "senderId": 1612008329,
        "url": "https://music.163.com/prime/m/gift-receive?u=b36a3abaff664215979307460377ae932d60c63ebba0467892aa77f8f9c9f950",
        "short_url": "http://t.cn/A6fMAXJo",
        "weibo_url": "https://weibo.com/detail/4654249538228145",
        "webUrl": "https://music.163.com/prime/m/gift-mypurchase?orderid=171849823&giftSrc=3&nm_style=sbt&bounces=false"
    },
    {
        "days": 5,
        "senderId": 1736524412,
        "url": "https://music.163.com/prime/m/gift-receive?u=d61e3fb01e7a4bce84594c9e7e75d7e7c1a2506ebaa3493bbd45430baaa58ed2",
        "short_url": "http://t.cn/A6fMbbcs",
        "weibo_url": "https://weibo.com/detail/4654273448648567",
        "webUrl": "https://music.163.com/prime/m/gift-mypurchase?orderid=171860437&giftSrc=3&nm_style=sbt&bounces=false"
    },
    {
        "days": 5,
        "senderId": 4908611853,
        "url": "https://music.163.com/prime/m/gift-receive?u=eebcd70d5ade492aad1e74b431e59fa53a31cc23b3254b5eab23952aa5aaf4c2",
        "short_url": "http://t.cn/A6fMVRAl",
        "weibo_url": "https://weibo.com/detail/4654287961981119",
        "webUrl": "https://music.163.com/prime/m/gift-mypurchase?orderid=171882742&giftSrc=3&nm_style=sbt&bounces=false"
    },
    {
        "days": 5,
        "senderId": 297853516,
        "url": "https://music.163.com/prime/m/gift-receive?u=f58f92d85f0a4167a394507e064d0f8054a7b33fb5344f6280b3581900bb2ab8",
        "short_url": "http://t.cn/A6fIrb7l",
        "weibo_url": "https://weibo.com/detail/4654163562333473",
        "webUrl": "https://music.163.com/prime/m/gift-mypurchase?orderid=171786664&giftSrc=3&nm_style=sbt&bounces=false"
    },
    {
        "days": 5,
        "senderId": 64884607,
        "url": "https://music.163.com/prime/m/gift-receive?u=0348e2fbbc464bb7be8be0efe3dc8eed2ac10018b4014ed583bd124f20f3f1bd",
        "short_url": "http://t.cn/A6fMzdL2",
        "weibo_url": "https://weibo.com/detail/4654234996573801",
        "webUrl": "https://music.163.com/prime/m/gift-mypurchase?orderid=171832203&giftSrc=3&nm_style=sbt&bounces=false"
    },
    {
        "days": 5,
        "senderId": 3719480529,
        "url": "https://music.163.com/prime/m/gift-receive?u=35e94265b98a477ea7bc48444e2f61bc1dd62185335147aa8ec8158ec8bb72c1",
        "short_url": "http://t.cn/A6fMvuDf",
        "weibo_url": "https://weibo.com/detail/4654210849183619",
        "webUrl": "https://music.163.com/prime/m/gift-mypurchase?orderid=171819088&giftSrc=3&nm_style=sbt&bounces=false"
    },
    {
        "days": 5,
        "senderId": 318398539,
        "url": "https://music.163.com/prime/m/gift-receive?u=8b647d77eecc4298a4120d3969fc676b63efe30f44984b548813b910bc2fb263",
        "short_url": "http://t.cn/A6fIeFLQ",
        "weibo_url": "https://weibo.com/detail/4654184474872146",
        "webUrl": "https://music.163.com/prime/m/gift-mypurchase?orderid=171800976&giftSrc=3&nm_style=sbt&bounces=false"
    },
    {
        "days": 5,
        "senderId": 303846317,
        "url": "https://music.163.com/prime/m/gift-receive?u=e92e8ad5ef314f2c936574500210f427689115a8cc3c4736aec089a62ff3722d",
        "short_url": "http://t.cn/A6fMwpSH",
        "weibo_url": "https://weibo.com/detail/4654244663400018",
        "webUrl": "https://music.163.com/prime/m/gift-mypurchase?orderid=171844032&giftSrc=3&nm_style=sbt&bounces=false"
    }
]