[
    {
        "days": 7,
        "goods": "黑胶VIP(7天)",
        "senderId": 1856766001,
        "url": "https://music.163.com/prime/m/gift-receive?u=04201bc45fb34ba2ab6b00dacfe09ba89da05ab93cd547b5b527ba238067cac0",
        "short_url": "http://t.cn/A6MLNmoM",
        "weibo_url": "https://weibo.com/detail/4683672017439312",
        "webUrl": "https://music.163.com/prime/m/gift-mypurchase?orderid=192943722&giftSrc=3&nm_style=sbt&bounces=false"
    },
    {
        "days": 7,
        "goods": "黑胶VIP(7天)",
        "senderId": 1542616659,
        "url": "https://music.163.com/prime/m/gift-receive?u=5748ce121c9b4f73833f7cfd8909d41b2706ed150ba74301a5e3b176ce964620&userid=1542616659&app_version=8.5.20",
        "short_url": "http://t.cn/A6My22Jg",
        "weibo_url": "https://weibo.com/detail/4683871746786671",
        "webUrl": "https://music.163.com/prime/m/gift-mypurchase?orderid=188650326&giftSrc=3&nm_style=sbt&bounces=false"
    },
    {
        "days": 7,
        "goods": "黑胶VIP(7天)",
        "senderId": 318172521,
        "url": "https://music.163.com/prime/m/gift-receive?u=a7201bdc8d8f4a328a95b6c1e55cf80d11c3816c0296420187b8f13d3689bb22",
        "short_url": "http://t.cn/A6MyzKHs",
        "weibo_url": "https://weibo.com/detail/4683853589644360",
        "webUrl": "https://music.163.com/prime/m/gift-mypurchase?orderid=193127583&giftSrc=3&nm_style=sbt&bounces=false"
    },
    {
        "days": 5,
        "goods": "黑胶VIP(5天)",
        "senderId": 339047646,
        "url": "https://music.163.com/prime/m/gift-receive?u=94eeeee9a0044b84b4cd0242168ab5cf75cd28ffd39043c3b7d8a3e7bb6bfe5d",
        "short_url": "http://t.cn/A6MAuaQ0",
        "weibo_url": "https://weibo.com/detail/4683177253931800",
        "webUrl": "https://music.163.com/prime/m/gift-mypurchase?orderid=188633914&giftSrc=3&nm_style=sbt&bounces=false"
    }
]