[
    {
        "days": 7,
        "goods": "黑胶VIP(7天)",
        "senderId": 1391837210,
        "url": "https://music.163.com/prime/m/gift-receive?p=1zy_NwCeJL6fBFuXrsiK7adP5fe92s9TSHVwTEPeEN81N258-7ux3GrD5uq_L5yogQBSt0Wx4AD42XADNUB3gbnuWBVSV_zZO5JIn7MD7ao&d=2jRo8qkUwd79aQPh4ZE51w",
        "short_url": "http://t.cn/A6SSBpxv",
        "weibo_url": "https://weibo.com/detail/4807601256401040",
        "webUrl": "https://music.163.com/prime/m/gift-mypurchase?orderid=326335875&giftSrc=3&nm_style=sbt&bounces=false"
    },
    {
        "days": 7,
        "goods": "黑胶VIP(7天)",
        "senderId": 560582119,
        "url": "https://music.163.com/prime/m/gift-receive?p=lHnrzCnEXpJXD0A28eQG7siWYN2puqCEzWFexc0R7dzNI_1F6yaw7kVyn24iAQCZrBQvsS_8ezg3Bdu3xfQAkvbPWHBJa4Sf-q5bYhpGxJs&d=zJQpGZn5U27WHs13O44HTA",
        "short_url": "https://weibo.cn/sinaurl?u=http%3A%2F%2F163.lu%2FRAig14",
        "weibo_url": "https://weibo.com/detail/4804457978399328",
        "webUrl": "https://music.163.com/prime/m/gift-mypurchase?orderid=315980388&giftSrc=3&nm_style=sbt&bounces=false"
    },
    {
        "days": 7,
        "goods": "黑胶VIP(7天)",
        "senderId": 1661870485,
        "url": "https://music.163.com/prime/m/gift-receive?d=7NkCCavBLk90Usw6zNNLwA&p=VY5gICpyeJcHhDGc6vS0g6Bj_h771UWBSb9tF9_6DHsCVz6CR3aXSGCep98cxnbLSWvfnY2zCUtdbZu3TaCZRlzMDvGrAoFIZ9oDR3jdTDI&userid=1661870485&app_version=8.8.20&dlt=0846",
        "short_url": "http://t.cn/A6SXKuBx",
        "weibo_url": "https://weibo.com/detail/4806830645319248",
        "webUrl": "https://music.163.com/prime/m/gift-mypurchase?orderid=315756730&giftSrc=3&nm_style=sbt&bounces=false"
    },
    {
        "days": 7,
        "goods": "黑胶VIP(7天)",
        "senderId": 1843522164,
        "url": "https://music.163.com/prime/m/gift-receive?d=_ClZUsfMfJu0juc8Ia_Ulw&p=shZQ_t-TSfGRgQ8k5ipxkDEa2rpTjs0q3fd6I7fdOBPU_vjjeVllrscenXL2zLjRIHaOec9wg3_XcxNPtuZEUUnUufnVYjVDgBphE1UhHoU&userid=1843522164&app_version=8.8.20&dlt=0846",
        "short_url": "http://t.cn/A6SSWmWj",
        "weibo_url": "https://weibo.com/detail/4807532696312419",
        "webUrl": "https://music.163.com/prime/m/gift-mypurchase?orderid=318732165&giftSrc=3&nm_style=sbt&bounces=false"
    },
    {
        "days": 7,
        "goods": "黑胶VIP(7天)",
        "senderId": 593182234,
        "url": "https://music.163.com/prime/m/gift-receive?p=VH4A-MEBOuUH3TKM83NknzLMEb13IZYX8HjcbouVhKke-V_GnRmCPRvadPHfzPkfrUO0zgd2t3ehdRYK4VeGcQVlXaPuaSv9o5rzx-_0pdA&d=P-qgPTImMATYbYhT2tgqHw",
        "short_url": "http://t.cn/A6SXO4sM",
        "weibo_url": "https://weibo.com/detail/4806856910836319",
        "webUrl": "https://music.163.com/prime/m/gift-mypurchase?orderid=325710972&giftSrc=3&nm_style=sbt&bounces=false"
    },
    {
        "days": 7,
        "goods": "黑胶VIP(7天)",
        "senderId": 47942909,
        "url": "https://music.163.com/prime/m/gift-receive?d=qe-esD0KNjiLNx6ZnUOgiA&p=CFt0sCywlhjbD7V0PY3jcKcr_0PcMpE4B5uRgMGfgXNf6jaTnTeSllfzg5wPgcyZjiJeZUsk55VDOiKUxBnh83K2mVu1X9Cxp0r-SsEi58s&userid=47942909&app_version=8.8.20&dlt=0846",
        "short_url": "http://t.cn/A6SXYx4X",
        "weibo_url": "https://weibo.com/detail/4806875797521320",
        "webUrl": "https://music.163.com/prime/m/gift-mypurchase?orderid=325701956&giftSrc=3&nm_style=sbt&bounces=false"
    },
    {
        "days": 7,
        "goods": "黑胶VIP(7天)",
        "senderId": 481568478,
        "url": "https://music.163.com/prime/m/gift-receive?p=722sIFYBW6eJnyKa3jThPtArmO5xXmLV6RtB2Tu3Z_EjIErQZjF0_gBWt19fgUgl7AUJqFF1ihl5R6JWj5Pjw58QcAAPhWyrqF8bYExKY-o&d=pZC3bn63RwISf2vImseSPA",
        "short_url": "https://weibo.cn/sinaurl?u=http%3A%2F%2F163.lu%2FUmUSA3",
        "weibo_url": "https://weibo.com/detail/4804540375238592",
        "webUrl": "https://music.163.com/prime/m/gift-mypurchase?orderid=323582398&giftSrc=3&nm_style=sbt&bounces=false"
    },
    {
        "days": 7,
        "goods": "黑胶VIP(7天)",
        "senderId": 384760945,
        "url": "https://music.163.com/prime/m/gift-receive?p=N0QRAnu_rzXy7iyCnO5QfVhFKyzfzPEGUEZ8IFWsT_r7dAsxXAJdgC5GZl9PAzkg4VRskOuZ4iO9B1Jtfmd4iGmUmVNZJ_f1YlsecLJnK9o&d=oW8H4aAAuuC29aLCXOKVYg",
        "short_url": "http://t.cn/A6SXCrEY",
        "weibo_url": "https://weibo.com/detail/4807578788561250",
        "webUrl": "https://music.163.com/prime/m/gift-mypurchase?orderid=324133340&giftSrc=3&nm_style=sbt&bounces=false"
    },
    {
        "days": 5,
        "goods": "黑胶VIP(5天)",
        "senderId": 1721884877,
        "url": "https://music.163.com/prime/m/gift-receive?p=fvEM26R-sJfRo_3wO-dDl4x2jhFitAsLowgwG4X_lw-0Xr6Kyr3QCIzblyXwAyQw5sDvRqRGPC3AnhMOMufDRksmG24tOLuF3yzkNx1Unas&d=tJeiLb1UCzeosiWgA15Keg",
        "short_url": "http://t.cn/A6SSQ4nQ",
        "weibo_url": "https://weibo.com/detail/4807556910815217",
        "webUrl": "https://music.163.com/prime/m/gift-mypurchase?orderid=326306920&giftSrc=3&nm_style=sbt&bounces=false"
    }
]